funct/Array.py
funct/__init__.py
funct/_lazy.py
funct/tests.py
Funct-0.9.2.dist-info/LICENCE
Funct-0.9.2.dist-info/METADATA
Funct-0.9.2.dist-info/WHEEL
Funct-0.9.2.dist-info/top_level.txt
Funct-0.9.2.dist-info/RECORD
