Metadata-Version: 2.1
Name: Funct
Version: 0.9.2
Summary: Functional Python Sequence
Home-page: https://github.com/lauriat/funct
Author: Lauri Tuominen
Author-email: lauri@port6.io
License: UNKNOWN
Platform: UNKNOWN
Classifier: Programming Language :: Python :: 3
Classifier: License :: OSI Approved :: MIT License
Classifier: Operating System :: OS Independent
Requires-Python: >=3.6
